LICENSE.txt
MANIFEST.in
README.md
pyproject.toml
requirements.txt
setup.py
auto_sklearn.egg-info/PKG-INFO
auto_sklearn.egg-info/SOURCES.txt
auto_sklearn.egg-info/dependency_links.txt
auto_sklearn.egg-info/requires.txt
auto_sklearn.egg-info/top_level.txt
autosklearn/__init__.py
autosklearn/__version__.py
autosklearn/askl_typing.py
autosklearn/automl.py
autosklearn/classification.py
autosklearn/constants.py
autosklearn/estimators.py
autosklearn/py.typed
autosklearn/regression.py
autosklearn/requirements.txt
autosklearn/smbo.py
autosklearn/automl_common/LICENSE
autosklearn/automl_common/README.md
autosklearn/automl_common/__init__.py
autosklearn/automl_common/common/__init__.py
autosklearn/automl_common/common/ensemble_building/__init__.py
autosklearn/automl_common/common/ensemble_building/abstract_ensemble.py
autosklearn/automl_common/common/utils/__init__.py
autosklearn/automl_common/common/utils/backend.py
autosklearn/automl_common/common/utils/logging_.py
autosklearn/data/__init__.py
autosklearn/data/abstract_data_manager.py
autosklearn/data/feature_validator.py
autosklearn/data/target_validator.py
autosklearn/data/validation.py
autosklearn/data/xy_data_manager.py
autosklearn/ensemble_building/__init__.py
autosklearn/ensemble_building/builder.py
autosklearn/ensemble_building/manager.py
autosklearn/ensemble_building/run.py
autosklearn/ensembles/__init__.py
autosklearn/ensembles/abstract_ensemble.py
autosklearn/ensembles/ensemble_selection.py
autosklearn/ensembles/multiobjective_dummy_ensemble.py
autosklearn/ensembles/singlebest_ensemble.py
autosklearn/evaluation/__init__.py
autosklearn/evaluation/abstract_evaluator.py
autosklearn/evaluation/splitter.py
autosklearn/evaluation/test_evaluator.py
autosklearn/evaluation/train_evaluator.py
autosklearn/evaluation/util.py
autosklearn/experimental/__init__.py
autosklearn/experimental/askl2.py
autosklearn/experimental/selector.py
autosklearn/experimental/balanced_accuracy/askl2_training_data.json
autosklearn/experimental/balanced_accuracy/askl2_portfolios/RF_None_10CV_iterative_es_if.json
autosklearn/experimental/balanced_accuracy/askl2_portfolios/RF_None_3CV_iterative_es_if.json
