Metadata-Version: 2.1
Name: auto-sklearn
Version: 0.15.0
Summary: Automated machine learning.
Home-page: https://automl.github.io/auto-sklearn
Author: Matthias Feurer
Author-email: feurerm@informatik.uni-freiburg.de
License: BSD3
Platform: Linux
Classifier: Environment :: Console
Classifier: Intended Audience :: Developers
Classifier: Intended Audience :: Education
Classifier: Intended Audience :: Science/Research
Classifier: Intended Audience :: Information Technology
Classifier: License :: OSI Approved :: BSD License
Classifier: Natural Language :: English
Classifier: Operating System :: OS Independent
Classifier: Topic :: Scientific/Engineering :: Artificial Intelligence
Classifier: Topic :: Scientific/Engineering :: Information Analysis
Classifier: Programming Language :: Python :: 3.7
Classifier: Programming Language :: Python :: 3.8
Classifier: Programming Language :: Python :: 3.9
Requires-Python: >=3.7
Provides-Extra: test
Provides-Extra: examples
Provides-Extra: docs
